{
    "Ram.AV011TQT": {
        "__class__":"Ram",
        "SKU":"AV011TQT",
        "ProductName": "16GB Corsair Vengance ram, full RGB, DDR4",
        "ProductImage": "https://cdn-icons-png.flaticon.com/512/5/5088.png",
        "ProductDescription": "Description. Lorem ipsum dolor sit amet, consectetur adipiscing elit, sed do eiusmod tempor incididunt ut labore et dolore magna aliqua.",
        "Price": 14.95,
        "Amount": 10,
        "Platform": "Desktop",
        
        "Brand": "Corsair",
        "Model":"Vengance",
        "Capacity": 16,
        "Speed": 2666
    },
    "Ram.AV342HSD": {
        "__class__":"Ram",
        "SKU":"AV342HSD",
        "ProductName": "8GB Crucial DDR4 SoDIMM",
        "ProductImage": "https://cdn-icons-png.flaticon.com/512/5/5088.png",
        "ProductDescription": "Description. Lorem ipsum dolor sit amet, consectetur adipiscing elit, sed do eiusmod tempor incididunt ut labore et dolore magna aliqua.",
        "Price": 10.95,
        "Amount": 10,
        "Platform": "Laptop",

        "Brand": "Crucial",
        "Model":"",
        "Capacity": 8,
        "Speed": 2400
    },
    "Cable.AV908HGS": {
        "__class__":"Cable",
        "SKU":"AV908HGS",
        "ProductName": "4ft HDMI Cable",
        "ProductImage": "https://cdn-icons-png.flaticon.com/512/5/5088.png",
        "ProductDescription": "Description. Lorem ipsum dolor sit amet, consectetur adipiscing elit, sed do eiusmod tempor incididunt ut labore et dolore magna aliqua.",
        "Price": 10.95,
        "Amount": 10,
        "Platform": "Desktop",

        "Type": "HDMI",
        "Length": 4
    },
    "Cable.AV847PEH": {
        "__class__":"Cable",
        "SKU":"AV847PEH",
        "ProductName": "4ft HDMI Cable",
        "ProductImage": "https://cdn-icons-png.flaticon.com/512/5/5088.png",
        "ProductDescription": "Description. Lorem ipsum dolor sit amet, consectetur adipiscing elit, sed do eiusmod tempor incididunt ut labore et dolore magna aliqua.",
        "Price": 10.95,
        "Amount": 10,
        "Platform": "Laptop",

        "Type": "HDMI",
        "Length": 4
    },
    "Cable.AV592LIS": {
        "__class__":"Cable",
        "SKU":"AV592LIS",
        "ProductName": "6ft DVI Cable",
        "ProductImage": "https://cdn-icons-png.flaticon.com/512/5/5088.png",
        "ProductDescription": "Description. Lorem ipsum dolor sit amet, consectetur adipiscing elit, sed do eiusmod tempor incididunt ut labore et dolore magna aliqua.",
        "Price": 10.95,
        "Amount": 10,
        "Platform": "Other",

        "Type": "DVI",
        "Length": 6
    },
    "Motherboard.AV098USE": {
        "__class__":"Motherboard",
        "SKU":"AV098USE",
        "ProductName": "Gigabyte H510M-H Motherboard",
        "ProductImage": "https://cdn-icons-png.flaticon.com/512/5/5088.png",
        "ProductDescription": "Description. Lorem ipsum dolor sit amet, consectetur adipiscing elit, sed do eiusmod tempor incididunt ut labore et dolore magna aliqua.",
        "Price": 109.95,
        "Amount": 10,
        "Platform": "Desktop",

        "Brand": "Gigabyte",
        "Model": "H510M-H",
        "Socket": "LGA 1200",
        "VideoOut": "VGA,HDMI,DVI",
        "RAMType": "DDR4",
        "RAMSlots": 2,
        "MAXRAMSPEED": 4200,
        "MINRAMSPEED": 2400,
        "NVMeSLOTS": 1
    },
    "Motherboard.AV825PBT": {
        "__class__":"Motherboard",
        "SKU":"AV825PBT",
        "ProductName": "Asus H460M Motherboard, Socket 1151",
        "ProductImage": "https://cdn-icons-png.flaticon.com/512/5/5088.png",
        "ProductDescription": "Description. Lorem ipsum dolor sit amet, consectetur adipiscing elit, sed do eiusmod tempor incididunt ut labore et dolore magna aliqua.",
        "Price": 95.95,
        "Amount": 10,
        "Platform": "Desktop",

        "Brand": "Asus",
        "Model": "H460M",
        "Socket": "LGA 1151",
        "VideoOut": "HDMI,DVI",
        "RAMType": "DDR4",
        "RAMSlots": 4,
        "MAXRAMSPEED": 4200,
        "MINRAMSPEED": 2400,
        "NVMeSLOTS": 2
    },
    "Case.AV826LUB": {
        "__class__":"Case",
        "SKU":"AV826LUB",
        "ProductName": "Coolermaster Elite 400, Full-ATX",
        "ProductImage": "https://cdn-icons-png.flaticon.com/512/5/5088.png",
        "ProductDescription": "Description. Lorem ipsum dolor sit amet, consectetur adipiscing elit, sed do eiusmod tempor incididunt ut labore et dolore magna aliqua.",
        "Price": 49.95,
        "Amount": 10,
        "Platform": "Desktop",

        "Brand": "Coolermaster",
        "Model": "400",
        "Size": "Full"
    },
    "CPU.AV204BAH": {
        "__class__":"CPU",
        "SKU":"AV204BAH",
        "ProductName": "10th Gen Intel Core i5-10600",
        "ProductImage": "https://cdn-icons-png.flaticon.com/512/5/5088.png",
        "ProductDescription": "Description. Lorem ipsum dolor sit amet, consectetur adipiscing elit, sed do eiusmod tempor incididunt ut labore et dolore magna aliqua.",
        "Price": 110.95,
        "Amount": 10,
        "Platform": "Desktop",

        "Brand": "Intel",
        "Model": "i5-10600",
        "Speed": 3.7,
        "Cores": 8
    },
    "CPU.AV925PEJ": {
        "__class__":"CPU",
        "SKU":"AV925PEJ",
        "ProductName": "9th Gen Intel Pentium",
        "ProductImage": "https://cdn-icons-png.flaticon.com/512/5/5088.png",
        "ProductDescription": "Description. Lorem ipsum dolor sit amet, consectetur adipiscing elit, sed do eiusmod tempor incididunt ut labore et dolore magna aliqua.",
        "Price": 89.95,
        "Amount": 10,
        "Platform": "Desktop",

        "Brand": "Intel",
        "Model": "G6400",
        "Speed": 2.9,
        "Cores": 4
    },
    "GPU.AV675LIY": {
        "__class__":"GPU",
        "SKU":"AV675LIY",
        "ProductName": "Gigabyte RTX 3070 Ti",
        "ProductImage": "https://cdn-icons-png.flaticon.com/512/5/5088.png",
        "ProductDescription": "Description. Lorem ipsum dolor sit amet, consectetur adipiscing elit, sed do eiusmod tempor incididunt ut labore et dolore magna aliqua.",
        "Price": 110.95,
        "Amount": 10,
        "Platform": "Desktop",

        "Brand": "Gigabyte",
        "Model": "3070 Ti"
    },
    "GPU.AV092QNY": {
        "__class__":"GPU",
        "SKU":"AV092QNY",
        "ProductName": "Asus RTX 3080 Super",
        "ProductImage": "https://cdn-icons-png.flaticon.com/512/5/5088.png",
        "ProductDescription": "Description. Lorem ipsum dolor sit amet, consectetur adipiscing elit, sed do eiusmod tempor incididunt ut labore et dolore magna aliqua.",
        "Price": 89.95,
        "Amount": 10,
        "Platform": "Desktop",

        "Brand": "Asus",
        "Model": "3080 Super"
    },
    "Monitor.AV443GGF": {
        "__class__":"Monitor",
        "SKU":"AV443GGF",
        "ProductName": "Asus 26\" Monitor DVI & HDMI Capable",
        "ProductImage": "https://cdn-icons-png.flaticon.com/512/5/5088.png",
        "ProductDescription": "Description. Lorem ipsum dolor sit amet, consectetur adipiscing elit, sed do eiusmod tempor incididunt ut labore et dolore magna aliqua.",
        "Price": 110.95,
        "Amount": 10,
        "Platform": "Desktop",
        
        "Brand": "Asus",
        "Ports": "DVI, HDMI",
        "Size": 26
    },
    "Monitor.AV342LLO": {
        "__class__":"Monitor",
        "SKU":"AV342LLO",
        "ProductName": "Asus 24\" Monitor VGA, DVI & HDMI Capable",
        "ProductImage": "https://cdn-icons-png.flaticon.com/512/5/5088.png",
        "ProductDescription": "Description. Lorem ipsum dolor sit amet, consectetur adipiscing elit, sed do eiusmod tempor incididunt ut labore et dolore magna aliqua.",
        "Price": 89.95,
        "Amount": 10,
        "Platform": "Desktop",

        "Brand": "Asus",
        "Ports": "HDMI, VGA, DVI",
        "Size": 24
    },
    "PSU.AV986CVS": {
        "__class__":"PSU",
        "SKU":"AV986CVS",
        "ProductName": "EVGA Full Modular 750w Power Supply",
        "ProductImage": "https://cdn-icons-png.flaticon.com/512/5/5088.png",
        "ProductDescription": "Description. Lorem ipsum dolor sit amet, consectetur adipiscing elit, sed do eiusmod tempor incididunt ut labore et dolore magna aliqua.",
        "Price": 99.95,
        "Amount": 10,
        "Platform": "Desktop",

        "Brand": "EVGA",
        "PowerAmount": 750
    },
    "PSU.AV522HEL": {
        "__class__":"PSU",
        "SKU":"AV522HEL",
        "ProductName": "EVGA 600w Power Supply",
        "ProductImage": "https://cdn-icons-png.flaticon.com/512/5/5088.png",
        "ProductDescription": "Description. Lorem ipsum dolor sit amet, consectetur adipiscing elit, sed do eiusmod tempor incididunt ut labore et dolore magna aliqua.",
        "Price": 79.95,
        "Amount": 10,
        "Platform": "Desktop",

        "Brand": "EVGA",
        "PowerAmount": 600
    },
    "SSD.AV126UYR": {
        "__class__":"SSD",
        "SKU":"AV126UYR",
        "ProductName": "500GB Samsung 2.5\" SATA SSD",
        "ProductImage": "https://cdn-icons-png.flaticon.com/512/5/5088.png",
        "ProductDescription": "Description. Lorem ipsum dolor sit amet, consectetur adipiscing elit, sed do eiusmod tempor incididunt ut labore et dolore magna aliqua.",
        "Price": 79.95,
        "Amount": 10,
        "Platform": "Desktop",

        "Brand": "Samsung",
        "Connection": "SATA",
        "Capacity": 500
    },
    "SSD.AV364POI": {
        "__class__":"SSD",
        "SKU":"AV364POI",
        "ProductName": "1TB Western Digital M.2 SSD",
        "ProductImage": "https://cdn-icons-png.flaticon.com/512/5/5088.png",
        "ProductDescription": "Description. Lorem ipsum dolor sit amet, consectetur adipiscing elit, sed do eiusmod tempor incididunt ut labore et dolore magna aliqua.",
        "Price": 99.95,
        "Amount": 10,
        "Platform": "Laptop",
        
        "Brand": "Western Digital",
        "Connection" : "M.2",
        "Capacity": 1000
    },
    "User.e9036e3e-6697-4e92-b3d1-0b1ff26be805": {
        "__class__":"User",
        "id":"e9036e3e-6697-4e92-b3d1-0b1ff26be805",
        "created_at": "2023-05-15T21:08:06.266803",
        "updated_at": "2023-05-15T21:08:06.266815",
        "Username": "Syssos",
        "Password": "plaintextftw",
        "Email": "totallymyemail@email.com"
    },
    "User.f558fce6-e02c-4e6c-93c8-401f8204da59": {
        "__class__":"User",
        "id":"f558fce6-e02c-4e6c-93c8-401f8204da59",
        "created_at": "2023-05-15T21:08:08.266803",
        "updated_at": "2023-05-15T21:08:08.266815",
        "Username": "TestAccount",
        "Password": "plaintextftw",
        "Email": "totallymyemail@email.com"
    },
    "Cart.903fc68a-e663-468c-9162-7dc570d9f613": {
        "__class__":"Cart",
        "id":"903fc68a-e663-468c-9162-7dc570d9f613",
        "created_at": "2023-05-15T21:08:08.266803",
        "updated_at": "2023-05-15T21:08:08.266815",
        "User": "TestAccount",
        "Items": ["AV522HEL", "AV126UYR"]
    }
}